fresh_blt/__init__.py
fresh_blt/cli.py
fresh_blt/export.py
fresh_blt/grammar.py
fresh_blt/parse.py
fresh_blt/py.typed
fresh_blt/models/__init__.py
fresh_blt/models/ballot.py
fresh_blt/models/candidate.py
fresh_blt/models/election.py
fresh_blt-0.3.0.dist-info/METADATA
fresh_blt-0.3.0.dist-info/WHEEL
fresh_blt-0.3.0.dist-info/entry_points.txt
fresh_blt-0.3.0.dist-info/licenses/LICENSE
fresh_blt-0.3.0.dist-info/RECORD
