Metadata-Version: 2.4
Name: fresh_blt
Version: 0.3.0
Summary: A CLI tool to parse and convert Opavote .blt ranked choice voter files.
Project-URL: Repository, https://github.com/mpancia/fresh_blt
Author-email: Matt Pancia <msp@themsp.org>
License-Expression: MIT
License-File: LICENSE
Classifier: Development Status :: 4 - Beta
Classifier: Intended Audience :: Developers
Classifier: Operating System :: OS Independent
Classifier: Programming Language :: Python
Classifier: Programming Language :: Python :: 3
Classifier: Programming Language :: Python :: 3.11
Classifier: Programming Language :: Python :: 3.12
Classifier: Programming Language :: Python :: 3.13
Classifier: Typing :: Typed
Requires-Python: <4.0,>=3.11
Requires-Dist: lark>=1.2.2
Requires-Dist: pandas>=2.3.1
Requires-Dist: pydantic>=2.11.7
Requires-Dist: rich>=14.0.0
Requires-Dist: typer>=0.15.0
